<?xml version="1.0" encoding="UTF-8" ?>
<!DOCTYPE mapper PUBLIC "-//mybatis.org//DTD Mapper 3.0//EN" "http://mybatis.org/dtd/mybatis-3-mapper.dtd" >
<mapper namespace="com.jakcray.springbootshiro.mybatisutils.mapper.UserInfoDAOMapper" >
  <resultMap id="BaseResultMap" type="com.jakcray.springbootshiro.mybatisutils.dao.UserInfoDAO" >
    <!--
      WARNING - @mbggenerated
      This element is automatically generated by MyBatis Generator, do not modify.
    -->
    <id column="iduserinfo" property="iduserinfo" jdbcType="VARCHAR" />
    <result column="b_name" property="bName" jdbcType="VARCHAR" />
    <result column="b_birthday" property="bBirthday" jdbcType="TIMESTAMP" />
    <result column="b_constellation" property="bConstellation" jdbcType="VARCHAR" />
    <result column="b_height" property="bHeight" jdbcType="VARCHAR" />
    <result column="b_annualsalary" property="bAnnualsalary" jdbcType="VARCHAR" />
    <result column="b_livecity" property="bLivecity" jdbcType="VARCHAR" />
    <result column="b_expect" property="bExpect" jdbcType="VARCHAR" />
    <result column="b_wechat" property="bWechat" jdbcType="VARCHAR" />
    <result column="i_nation" property="iNation" jdbcType="VARCHAR" />
    <result column="i_hometown" property="iHometown" jdbcType="VARCHAR" />
    <result column="i_naritalstatus" property="iNaritalstatus" jdbcType="VARCHAR" />
    <result column="i_occupation" property="iOccupation" jdbcType="VARCHAR" />
    <result column="i_faith" property="iFaith" jdbcType="VARCHAR" />
    <result column="i_drinkwine" property="iDrinkwine" jdbcType="VARCHAR" />
    <result column="i_smoking" property="iSmoking" jdbcType="VARCHAR" />
    <result column="i_sortinhome" property="iSortinhome" jdbcType="VARCHAR" />
    <result column="i_hasson" property="iHasson" jdbcType="VARCHAR" />
    <result column="i_weight" property="iWeight" jdbcType="VARCHAR" />
    <result column="s_age" property="sAge" jdbcType="VARCHAR" />
    <result column="s_height" property="sHeight" jdbcType="VARCHAR" />
    <result column="s_annualincome" property="sAnnualincome" jdbcType="VARCHAR" />
    <result column="s_hometown" property="sHometown" jdbcType="VARCHAR" />
    <result column="s_maritalstatus" property="sMaritalstatus" jdbcType="VARCHAR" />
    <result column="s_faith" property="sFaith" jdbcType="VARCHAR" />
    <result column="s_drink" property="sDrink" jdbcType="VARCHAR" />
    <result column="s_smoking" property="sSmoking" jdbcType="VARCHAR" />
    <result column="s_hasson" property="sHasson" jdbcType="VARCHAR" />
    <result column="s_weight" property="sWeight" jdbcType="VARCHAR" />
    <result column="s_constellation" property="sConstellation" jdbcType="VARCHAR" />
    <result column="p_moive" property="pMoive" jdbcType="VARCHAR" />
    <result column="p_music" property="pMusic" jdbcType="VARCHAR" />
    <result column="p_book" property="pBook" jdbcType="VARCHAR" />
    <result column="p_food" property="pFood" jdbcType="VARCHAR" />
    <result column="p_sport" property="pSport" jdbcType="VARCHAR" />
    <result column="iduserextrainfo" property="iduserextrainfo" jdbcType="VARCHAR" />
    <result column="iduser" property="iduser" jdbcType="VARCHAR" />
    <result column="addtime" property="addtime" jdbcType="TIMESTAMP" />
    <result column="ts" property="ts" jdbcType="TIMESTAMP" />
  </resultMap>
  <sql id="Example_Where_Clause" >
    <!--
      WARNING - @mbggenerated
      This element is automatically generated by MyBatis Generator, do not modify.
    -->
    <where >
      <foreach collection="oredCriteria" item="criteria" separator="or" >
        <if test="criteria.valid" >
          <trim prefix="(" suffix=")" prefixOverrides="and" >
            <foreach collection="criteria.criteria" item="criterion" >
              <choose >
                <when test="criterion.noValue" >
                  and ${criterion.condition}
                </when>
                <when test="criterion.singleValue" >
                  and ${criterion.condition} #{criterion.value}
                </when>
                <when test="criterion.betweenValue" >
                  and ${criterion.condition} #{criterion.value} and #{criterion.secondValue}
                </when>
                <when test="criterion.listValue" >
                  and ${criterion.condition}
                  <foreach collection="criterion.value" item="listItem" open="(" close=")" separator="," >
                    #{listItem}
                  </foreach>
                </when>
              </choose>
            </foreach>
          </trim>
        </if>
      </foreach>
    </where>
  </sql>
  <sql id="Update_By_Example_Where_Clause" >
    <!--
      WARNING - @mbggenerated
      This element is automatically generated by MyBatis Generator, do not modify.
    -->
    <where >
      <foreach collection="example.oredCriteria" item="criteria" separator="or" >
        <if test="criteria.valid" >
          <trim prefix="(" suffix=")" prefixOverrides="and" >
            <foreach collection="criteria.criteria" item="criterion" >
              <choose >
                <when test="criterion.noValue" >
                  and ${criterion.condition}
                </when>
                <when test="criterion.singleValue" >
                  and ${criterion.condition} #{criterion.value}
                </when>
                <when test="criterion.betweenValue" >
                  and ${criterion.condition} #{criterion.value} and #{criterion.secondValue}
                </when>
                <when test="criterion.listValue" >
                  and ${criterion.condition}
                  <foreach collection="criterion.value" item="listItem" open="(" close=")" separator="," >
                    #{listItem}
                  </foreach>
                </when>
              </choose>
            </foreach>
          </trim>
        </if>
      </foreach>
    </where>
  </sql>
  <sql id="Base_Column_List" >
    <!--
      WARNING - @mbggenerated
      This element is automatically generated by MyBatis Generator, do not modify.
    -->
    iduserinfo, b_name, b_birthday, b_constellation, b_height, b_annualsalary, b_livecity, 
    b_expect, b_wechat, i_nation, i_hometown, i_naritalstatus, i_occupation, i_faith, 
    i_drinkwine, i_smoking, i_sortinhome, i_hasson, i_weight, s_age, s_height, s_annualincome, 
    s_hometown, s_maritalstatus, s_faith, s_drink, s_smoking, s_hasson, s_weight, s_constellation, 
    p_moive, p_music, p_book, p_food, p_sport, iduserextrainfo, iduser, addtime, ts
  </sql>
  <select id="selectByExample" resultMap="BaseResultMap" parameterType="com.jakcray.springbootshiro.mybatisutils.dao.UserInfoDAOExample" >
    <!--
      WARNING - @mbggenerated
      This element is automatically generated by MyBatis Generator, do not modify.
    -->
    select
    <if test="distinct" >
      distinct
    </if>
    'true' as QUERYID,
    <include refid="Base_Column_List" />
    from userinfo
    <if test="_parameter != null" >
      <include refid="Example_Where_Clause" />
    </if>
    <if test="orderByClause != null" >
      order by ${orderByClause}
    </if>
  </select>
  <select id="selectByPrimaryKey" resultMap="BaseResultMap" parameterType="java.lang.String" >
    <!--
      WARNING - @mbggenerated
      This element is automatically generated by MyBatis Generator, do not modify.
    -->
    select 
    <include refid="Base_Column_List" />
    from userinfo
    where iduserinfo = #{iduserinfo,jdbcType=VARCHAR}
  </select>
  <delete id="deleteByPrimaryKey" parameterType="java.lang.String" >
    <!--
      WARNING - @mbggenerated
      This element is automatically generated by MyBatis Generator, do not modify.
    -->
    delete from userinfo
    where iduserinfo = #{iduserinfo,jdbcType=VARCHAR}
  </delete>
  <delete id="deleteByExample" parameterType="com.jakcray.springbootshiro.mybatisutils.dao.UserInfoDAOExample" >
    <!--
      WARNING - @mbggenerated
      This element is automatically generated by MyBatis Generator, do not modify.
    -->
    delete from userinfo
    <if test="_parameter != null" >
      <include refid="Example_Where_Clause" />
    </if>
  </delete>
  <insert id="insert" parameterType="com.jakcray.springbootshiro.mybatisutils.dao.UserInfoDAO" >
    <!--
      WARNING - @mbggenerated
      This element is automatically generated by MyBatis Generator, do not modify.
    -->
    insert into userinfo (iduserinfo, b_name, b_birthday, 
      b_constellation, b_height, b_annualsalary, 
      b_livecity, b_expect, b_wechat, 
      i_nation, i_hometown, i_naritalstatus, 
      i_occupation, i_faith, i_drinkwine, 
      i_smoking, i_sortinhome, i_hasson, 
      i_weight, s_age, s_height, 
      s_annualincome, s_hometown, s_maritalstatus, 
      s_faith, s_drink, s_smoking, 
      s_hasson, s_weight, s_constellation, 
      p_moive, p_music, p_book, 
      p_food, p_sport, iduserextrainfo, 
      iduser, addtime, ts
      )
    values (#{iduserinfo,jdbcType=VARCHAR}, #{bName,jdbcType=VARCHAR}, #{bBirthday,jdbcType=TIMESTAMP}, 
      #{bConstellation,jdbcType=VARCHAR}, #{bHeight,jdbcType=VARCHAR}, #{bAnnualsalary,jdbcType=VARCHAR}, 
      #{bLivecity,jdbcType=VARCHAR}, #{bExpect,jdbcType=VARCHAR}, #{bWechat,jdbcType=VARCHAR}, 
      #{iNation,jdbcType=VARCHAR}, #{iHometown,jdbcType=VARCHAR}, #{iNaritalstatus,jdbcType=VARCHAR}, 
      #{iOccupation,jdbcType=VARCHAR}, #{iFaith,jdbcType=VARCHAR}, #{iDrinkwine,jdbcType=VARCHAR}, 
      #{iSmoking,jdbcType=VARCHAR}, #{iSortinhome,jdbcType=VARCHAR}, #{iHasson,jdbcType=VARCHAR}, 
      #{iWeight,jdbcType=VARCHAR}, #{sAge,jdbcType=VARCHAR}, #{sHeight,jdbcType=VARCHAR}, 
      #{sAnnualincome,jdbcType=VARCHAR}, #{sHometown,jdbcType=VARCHAR}, #{sMaritalstatus,jdbcType=VARCHAR}, 
      #{sFaith,jdbcType=VARCHAR}, #{sDrink,jdbcType=VARCHAR}, #{sSmoking,jdbcType=VARCHAR}, 
      #{sHasson,jdbcType=VARCHAR}, #{sWeight,jdbcType=VARCHAR}, #{sConstellation,jdbcType=VARCHAR}, 
      #{pMoive,jdbcType=VARCHAR}, #{pMusic,jdbcType=VARCHAR}, #{pBook,jdbcType=VARCHAR}, 
      #{pFood,jdbcType=VARCHAR}, #{pSport,jdbcType=VARCHAR}, #{iduserextrainfo,jdbcType=VARCHAR}, 
      #{iduser,jdbcType=VARCHAR}, #{addtime,jdbcType=TIMESTAMP}, #{ts,jdbcType=TIMESTAMP}
      )
  </insert>
  <insert id="insertSelective" parameterType="com.jakcray.springbootshiro.mybatisutils.dao.UserInfoDAO" >
    <!--
      WARNING - @mbggenerated
      This element is automatically generated by MyBatis Generator, do not modify.
    -->
    insert into userinfo
    <trim prefix="(" suffix=")" suffixOverrides="," >
      <if test="iduserinfo != null" >
        iduserinfo,
      </if>
      <if test="bName != null" >
        b_name,
      </if>
      <if test="bBirthday != null" >
        b_birthday,
      </if>
      <if test="bConstellation != null" >
        b_constellation,
      </if>
      <if test="bHeight != null" >
        b_height,
      </if>
      <if test="bAnnualsalary != null" >
        b_annualsalary,
      </if>
      <if test="bLivecity != null" >
        b_livecity,
      </if>
      <if test="bExpect != null" >
        b_expect,
      </if>
      <if test="bWechat != null" >
        b_wechat,
      </if>
      <if test="iNation != null" >
        i_nation,
      </if>
      <if test="iHometown != null" >
        i_hometown,
      </if>
      <if test="iNaritalstatus != null" >
        i_naritalstatus,
      </if>
      <if test="iOccupation != null" >
        i_occupation,
      </if>
      <if test="iFaith != null" >
        i_faith,
      </if>
      <if test="iDrinkwine != null" >
        i_drinkwine,
      </if>
      <if test="iSmoking != null" >
        i_smoking,
      </if>
      <if test="iSortinhome != null" >
        i_sortinhome,
      </if>
      <if test="iHasson != null" >
        i_hasson,
      </if>
      <if test="iWeight != null" >
        i_weight,
      </if>
      <if test="sAge != null" >
        s_age,
      </if>
      <if test="sHeight != null" >
        s_height,
      </if>
      <if test="sAnnualincome != null" >
        s_annualincome,
      </if>
      <if test="sHometown != null" >
        s_hometown,
      </if>
      <if test="sMaritalstatus != null" >
        s_maritalstatus,
      </if>
      <if test="sFaith != null" >
        s_faith,
      </if>
      <if test="sDrink != null" >
        s_drink,
      </if>
      <if test="sSmoking != null" >
        s_smoking,
      </if>
      <if test="sHasson != null" >
        s_hasson,
      </if>
      <if test="sWeight != null" >
        s_weight,
      </if>
      <if test="sConstellation != null" >
        s_constellation,
      </if>
      <if test="pMoive != null" >
        p_moive,
      </if>
      <if test="pMusic != null" >
        p_music,
      </if>
      <if test="pBook != null" >
        p_book,
      </if>
      <if test="pFood != null" >
        p_food,
      </if>
      <if test="pSport != null" >
        p_sport,
      </if>
      <if test="iduserextrainfo != null" >
        iduserextrainfo,
      </if>
      <if test="iduser != null" >
        iduser,
      </if>
      <if test="addtime != null" >
        addtime,
      </if>
      <if test="ts != null" >
        ts,
      </if>
    </trim>
    <trim prefix="values (" suffix=")" suffixOverrides="," >
      <if test="iduserinfo != null" >
        #{iduserinfo,jdbcType=VARCHAR},
      </if>
      <if test="bName != null" >
        #{bName,jdbcType=VARCHAR},
      </if>
      <if test="bBirthday != null" >
        #{bBirthday,jdbcType=TIMESTAMP},
      </if>
      <if test="bConstellation != null" >
        #{bConstellation,jdbcType=VARCHAR},
      </if>
      <if test="bHeight != null" >
        #{bHeight,jdbcType=VARCHAR},
      </if>
      <if test="bAnnualsalary != null" >
        #{bAnnualsalary,jdbcType=VARCHAR},
      </if>
      <if test="bLivecity != null" >
        #{bLivecity,jdbcType=VARCHAR},
      </if>
      <if test="bExpect != null" >
        #{bExpect,jdbcType=VARCHAR},
      </if>
      <if test="bWechat != null" >
        #{bWechat,jdbcType=VARCHAR},
      </if>
      <if test="iNation != null" >
        #{iNation,jdbcType=VARCHAR},
      </if>
      <if test="iHometown != null" >
        #{iHometown,jdbcType=VARCHAR},
      </if>
      <if test="iNaritalstatus != null" >
        #{iNaritalstatus,jdbcType=VARCHAR},
      </if>
      <if test="iOccupation != null" >
        #{iOccupation,jdbcType=VARCHAR},
      </if>
      <if test="iFaith != null" >
        #{iFaith,jdbcType=VARCHAR},
      </if>
      <if test="iDrinkwine != null" >
        #{iDrinkwine,jdbcType=VARCHAR},
      </if>
      <if test="iSmoking != null" >
        #{iSmoking,jdbcType=VARCHAR},
      </if>
      <if test="iSortinhome != null" >
        #{iSortinhome,jdbcType=VARCHAR},
      </if>
      <if test="iHasson != null" >
        #{iHasson,jdbcType=VARCHAR},
      </if>
      <if test="iWeight != null" >
        #{iWeight,jdbcType=VARCHAR},
      </if>
      <if test="sAge != null" >
        #{sAge,jdbcType=VARCHAR},
      </if>
      <if test="sHeight != null" >
        #{sHeight,jdbcType=VARCHAR},
      </if>
      <if test="sAnnualincome != null" >
        #{sAnnualincome,jdbcType=VARCHAR},
      </if>
      <if test="sHometown != null" >
        #{sHometown,jdbcType=VARCHAR},
      </if>
      <if test="sMaritalstatus != null" >
        #{sMaritalstatus,jdbcType=VARCHAR},
      </if>
      <if test="sFaith != null" >
        #{sFaith,jdbcType=VARCHAR},
      </if>
      <if test="sDrink != null" >
        #{sDrink,jdbcType=VARCHAR},
      </if>
      <if test="sSmoking != null" >
        #{sSmoking,jdbcType=VARCHAR},
      </if>
      <if test="sHasson != null" >
        #{sHasson,jdbcType=VARCHAR},
      </if>
      <if test="sWeight != null" >
        #{sWeight,jdbcType=VARCHAR},
      </if>
      <if test="sConstellation != null" >
        #{sConstellation,jdbcType=VARCHAR},
      </if>
      <if test="pMoive != null" >
        #{pMoive,jdbcType=VARCHAR},
      </if>
      <if test="pMusic != null" >
        #{pMusic,jdbcType=VARCHAR},
      </if>
      <if test="pBook != null" >
        #{pBook,jdbcType=VARCHAR},
      </if>
      <if test="pFood != null" >
        #{pFood,jdbcType=VARCHAR},
      </if>
      <if test="pSport != null" >
        #{pSport,jdbcType=VARCHAR},
      </if>
      <if test="iduserextrainfo != null" >
        #{iduserextrainfo,jdbcType=VARCHAR},
      </if>
      <if test="iduser != null" >
        #{iduser,jdbcType=VARCHAR},
      </if>
      <if test="addtime != null" >
        #{addtime,jdbcType=TIMESTAMP},
      </if>
      <if test="ts != null" >
        #{ts,jdbcType=TIMESTAMP},
      </if>
    </trim>
  </insert>
  <select id="countByExample" parameterType="com.jakcray.springbootshiro.mybatisutils.dao.UserInfoDAOExample" resultType="java.lang.Integer" >
    <!--
      WARNING - @mbggenerated
      This element is automatically generated by MyBatis Generator, do not modify.
    -->
    select count(*) from userinfo
    <if test="_parameter != null" >
      <include refid="Example_Where_Clause" />
    </if>
  </select>
  <update id="updateByExampleSelective" parameterType="map" >
    <!--
      WARNING - @mbggenerated
      This element is automatically generated by MyBatis Generator, do not modify.
    -->
    update userinfo
    <set >
      <if test="record.iduserinfo != null" >
        iduserinfo = #{record.iduserinfo,jdbcType=VARCHAR},
      </if>
      <if test="record.bName != null" >
        b_name = #{record.bName,jdbcType=VARCHAR},
      </if>
      <if test="record.bBirthday != null" >
        b_birthday = #{record.bBirthday,jdbcType=TIMESTAMP},
      </if>
      <if test="record.bConstellation != null" >
        b_constellation = #{record.bConstellation,jdbcType=VARCHAR},
      </if>
      <if test="record.bHeight != null" >
        b_height = #{record.bHeight,jdbcType=VARCHAR},
      </if>
      <if test="record.bAnnualsalary != null" >
        b_annualsalary = #{record.bAnnualsalary,jdbcType=VARCHAR},
      </if>
      <if test="record.bLivecity != null" >
        b_livecity = #{record.bLivecity,jdbcType=VARCHAR},
      </if>
      <if test="record.bExpect != null" >
        b_expect = #{record.bExpect,jdbcType=VARCHAR},
      </if>
      <if test="record.bWechat != null" >
        b_wechat = #{record.bWechat,jdbcType=VARCHAR},
      </if>
      <if test="record.iNation != null" >
        i_nation = #{record.iNation,jdbcType=VARCHAR},
      </if>
      <if test="record.iHometown != null" >
        i_hometown = #{record.iHometown,jdbcType=VARCHAR},
      </if>
      <if test="record.iNaritalstatus != null" >
        i_naritalstatus = #{record.iNaritalstatus,jdbcType=VARCHAR},
      </if>
      <if test="record.iOccupation != null" >
        i_occupation = #{record.iOccupation,jdbcType=VARCHAR},
      </if>
      <if test="record.iFaith != null" >
        i_faith = #{record.iFaith,jdbcType=VARCHAR},
      </if>
      <if test="record.iDrinkwine != null" >
        i_drinkwine = #{record.iDrinkwine,jdbcType=VARCHAR},
      </if>
      <if test="record.iSmoking != null" >
        i_smoking = #{record.iSmoking,jdbcType=VARCHAR},
      </if>
      <if test="record.iSortinhome != null" >
        i_sortinhome = #{record.iSortinhome,jdbcType=VARCHAR},
      </if>
      <if test="record.iHasson != null" >
        i_hasson = #{record.iHasson,jdbcType=VARCHAR},
      </if>
      <if test="record.iWeight != null" >
        i_weight = #{record.iWeight,jdbcType=VARCHAR},
      </if>
      <if test="record.sAge != null" >
        s_age = #{record.sAge,jdbcType=VARCHAR},
      </if>
      <if test="record.sHeight != null" >
        s_height = #{record.sHeight,jdbcType=VARCHAR},
      </if>
      <if test="record.sAnnualincome != null" >
        s_annualincome = #{record.sAnnualincome,jdbcType=VARCHAR},
      </if>
      <if test="record.sHometown != null" >
        s_hometown = #{record.sHometown,jdbcType=VARCHAR},
      </if>
      <if test="record.sMaritalstatus != null" >
        s_maritalstatus = #{record.sMaritalstatus,jdbcType=VARCHAR},
      </if>
      <if test="record.sFaith != null" >
        s_faith = #{record.sFaith,jdbcType=VARCHAR},
      </if>
      <if test="record.sDrink != null" >
        s_drink = #{record.sDrink,jdbcType=VARCHAR},
      </if>
      <if test="record.sSmoking != null" >
        s_smoking = #{record.sSmoking,jdbcType=VARCHAR},
      </if>
      <if test="record.sHasson != null" >
        s_hasson = #{record.sHasson,jdbcType=VARCHAR},
      </if>
      <if test="record.sWeight != null" >
        s_weight = #{record.sWeight,jdbcType=VARCHAR},
      </if>
      <if test="record.sConstellation != null" >
        s_constellation = #{record.sConstellation,jdbcType=VARCHAR},
      </if>
      <if test="record.pMoive != null" >
        p_moive = #{record.pMoive,jdbcType=VARCHAR},
      </if>
      <if test="record.pMusic != null" >
        p_music = #{record.pMusic,jdbcType=VARCHAR},
      </if>
      <if test="record.pBook != null" >
        p_book = #{record.pBook,jdbcType=VARCHAR},
      </if>
      <if test="record.pFood != null" >
        p_food = #{record.pFood,jdbcType=VARCHAR},
      </if>
      <if test="record.pSport != null" >
        p_sport = #{record.pSport,jdbcType=VARCHAR},
      </if>
      <if test="record.iduserextrainfo != null" >
        iduserextrainfo = #{record.iduserextrainfo,jdbcType=VARCHAR},
      </if>
      <if test="record.iduser != null" >
        iduser = #{record.iduser,jdbcType=VARCHAR},
      </if>
      <if test="record.addtime != null" >
        addtime = #{record.addtime,jdbcType=TIMESTAMP},
      </if>
      <if test="record.ts != null" >
        ts = #{record.ts,jdbcType=TIMESTAMP},
      </if>
    </set>
    <if test="_parameter != null" >
      <include refid="Update_By_Example_Where_Clause" />
    </if>
  </update>
  <update id="updateByExample" parameterType="map" >
    <!--
      WARNING - @mbggenerated
      This element is automatically generated by MyBatis Generator, do not modify.
    -->
    update userinfo
    set iduserinfo = #{record.iduserinfo,jdbcType=VARCHAR},
      b_name = #{record.bName,jdbcType=VARCHAR},
      b_birthday = #{record.bBirthday,jdbcType=TIMESTAMP},
      b_constellation = #{record.bConstellation,jdbcType=VARCHAR},
      b_height = #{record.bHeight,jdbcType=VARCHAR},
      b_annualsalary = #{record.bAnnualsalary,jdbcType=VARCHAR},
      b_livecity = #{record.bLivecity,jdbcType=VARCHAR},
      b_expect = #{record.bExpect,jdbcType=VARCHAR},
      b_wechat = #{record.bWechat,jdbcType=VARCHAR},
      i_nation = #{record.iNation,jdbcType=VARCHAR},
      i_hometown = #{record.iHometown,jdbcType=VARCHAR},
      i_naritalstatus = #{record.iNaritalstatus,jdbcType=VARCHAR},
      i_occupation = #{record.iOccupation,jdbcType=VARCHAR},
      i_faith = #{record.iFaith,jdbcType=VARCHAR},
      i_drinkwine = #{record.iDrinkwine,jdbcType=VARCHAR},
      i_smoking = #{record.iSmoking,jdbcType=VARCHAR},
      i_sortinhome = #{record.iSortinhome,jdbcType=VARCHAR},
      i_hasson = #{record.iHasson,jdbcType=VARCHAR},
      i_weight = #{record.iWeight,jdbcType=VARCHAR},
      s_age = #{record.sAge,jdbcType=VARCHAR},
      s_height = #{record.sHeight,jdbcType=VARCHAR},
      s_annualincome = #{record.sAnnualincome,jdbcType=VARCHAR},
      s_hometown = #{record.sHometown,jdbcType=VARCHAR},
      s_maritalstatus = #{record.sMaritalstatus,jdbcType=VARCHAR},
      s_faith = #{record.sFaith,jdbcType=VARCHAR},
      s_drink = #{record.sDrink,jdbcType=VARCHAR},
      s_smoking = #{record.sSmoking,jdbcType=VARCHAR},
      s_hasson = #{record.sHasson,jdbcType=VARCHAR},
      s_weight = #{record.sWeight,jdbcType=VARCHAR},
      s_constellation = #{record.sConstellation,jdbcType=VARCHAR},
      p_moive = #{record.pMoive,jdbcType=VARCHAR},
      p_music = #{record.pMusic,jdbcType=VARCHAR},
      p_book = #{record.pBook,jdbcType=VARCHAR},
      p_food = #{record.pFood,jdbcType=VARCHAR},
      p_sport = #{record.pSport,jdbcType=VARCHAR},
      iduserextrainfo = #{record.iduserextrainfo,jdbcType=VARCHAR},
      iduser = #{record.iduser,jdbcType=VARCHAR},
      addtime = #{record.addtime,jdbcType=TIMESTAMP},
      ts = #{record.ts,jdbcType=TIMESTAMP}
    <if test="_parameter != null" >
      <include refid="Update_By_Example_Where_Clause" />
    </if>
  </update>
  <update id="updateByPrimaryKeySelective" parameterType="com.jakcray.springbootshiro.mybatisutils.dao.UserInfoDAO" >
    <!--
      WARNING - @mbggenerated
      This element is automatically generated by MyBatis Generator, do not modify.
    -->
    update userinfo
    <set >
      <if test="bName != null" >
        b_name = #{bName,jdbcType=VARCHAR},
      </if>
      <if test="bBirthday != null" >
        b_birthday = #{bBirthday,jdbcType=TIMESTAMP},
      </if>
      <if test="bConstellation != null" >
        b_constellation = #{bConstellation,jdbcType=VARCHAR},
      </if>
      <if test="bHeight != null" >
        b_height = #{bHeight,jdbcType=VARCHAR},
      </if>
      <if test="bAnnualsalary != null" >
        b_annualsalary = #{bAnnualsalary,jdbcType=VARCHAR},
      </if>
      <if test="bLivecity != null" >
        b_livecity = #{bLivecity,jdbcType=VARCHAR},
      </if>
      <if test="bExpect != null" >
        b_expect = #{bExpect,jdbcType=VARCHAR},
      </if>
      <if test="bWechat != null" >
        b_wechat = #{bWechat,jdbcType=VARCHAR},
      </if>
      <if test="iNation != null" >
        i_nation = #{iNation,jdbcType=VARCHAR},
      </if>
      <if test="iHometown != null" >
        i_hometown = #{iHometown,jdbcType=VARCHAR},
      </if>
      <if test="iNaritalstatus != null" >
        i_naritalstatus = #{iNaritalstatus,jdbcType=VARCHAR},
      </if>
      <if test="iOccupation != null" >
        i_occupation = #{iOccupation,jdbcType=VARCHAR},
      </if>
      <if test="iFaith != null" >
        i_faith = #{iFaith,jdbcType=VARCHAR},
      </if>
      <if test="iDrinkwine != null" >
        i_drinkwine = #{iDrinkwine,jdbcType=VARCHAR},
      </if>
      <if test="iSmoking != null" >
        i_smoking = #{iSmoking,jdbcType=VARCHAR},
      </if>
      <if test="iSortinhome != null" >
        i_sortinhome = #{iSortinhome,jdbcType=VARCHAR},
      </if>
      <if test="iHasson != null" >
        i_hasson = #{iHasson,jdbcType=VARCHAR},
      </if>
      <if test="iWeight != null" >
        i_weight = #{iWeight,jdbcType=VARCHAR},
      </if>
      <if test="sAge != null" >
        s_age = #{sAge,jdbcType=VARCHAR},
      </if>
      <if test="sHeight != null" >
        s_height = #{sHeight,jdbcType=VARCHAR},
      </if>
      <if test="sAnnualincome != null" >
        s_annualincome = #{sAnnualincome,jdbcType=VARCHAR},
      </if>
      <if test="sHometown != null" >
        s_hometown = #{sHometown,jdbcType=VARCHAR},
      </if>
      <if test="sMaritalstatus != null" >
        s_maritalstatus = #{sMaritalstatus,jdbcType=VARCHAR},
      </if>
      <if test="sFaith != null" >
        s_faith = #{sFaith,jdbcType=VARCHAR},
      </if>
      <if test="sDrink != null" >
        s_drink = #{sDrink,jdbcType=VARCHAR},
      </if>
      <if test="sSmoking != null" >
        s_smoking = #{sSmoking,jdbcType=VARCHAR},
      </if>
      <if test="sHasson != null" >
        s_hasson = #{sHasson,jdbcType=VARCHAR},
      </if>
      <if test="sWeight != null" >
        s_weight = #{sWeight,jdbcType=VARCHAR},
      </if>
      <if test="sConstellation != null" >
        s_constellation = #{sConstellation,jdbcType=VARCHAR},
      </if>
      <if test="pMoive != null" >
        p_moive = #{pMoive,jdbcType=VARCHAR},
      </if>
      <if test="pMusic != null" >
        p_music = #{pMusic,jdbcType=VARCHAR},
      </if>
      <if test="pBook != null" >
        p_book = #{pBook,jdbcType=VARCHAR},
      </if>
      <if test="pFood != null" >
        p_food = #{pFood,jdbcType=VARCHAR},
      </if>
      <if test="pSport != null" >
        p_sport = #{pSport,jdbcType=VARCHAR},
      </if>
      <if test="iduserextrainfo != null" >
        iduserextrainfo = #{iduserextrainfo,jdbcType=VARCHAR},
      </if>
      <if test="iduser != null" >
        iduser = #{iduser,jdbcType=VARCHAR},
      </if>
      <if test="addtime != null" >
        addtime = #{addtime,jdbcType=TIMESTAMP},
      </if>
      <if test="ts != null" >
        ts = #{ts,jdbcType=TIMESTAMP},
      </if>
    </set>
    where iduserinfo = #{iduserinfo,jdbcType=VARCHAR}
  </update>
  <update id="updateByPrimaryKey" parameterType="com.jakcray.springbootshiro.mybatisutils.dao.UserInfoDAO" >
    <!--
      WARNING - @mbggenerated
      This element is automatically generated by MyBatis Generator, do not modify.
    -->
    update userinfo
    set b_name = #{bName,jdbcType=VARCHAR},
      b_birthday = #{bBirthday,jdbcType=TIMESTAMP},
      b_constellation = #{bConstellation,jdbcType=VARCHAR},
      b_height = #{bHeight,jdbcType=VARCHAR},
      b_annualsalary = #{bAnnualsalary,jdbcType=VARCHAR},
      b_livecity = #{bLivecity,jdbcType=VARCHAR},
      b_expect = #{bExpect,jdbcType=VARCHAR},
      b_wechat = #{bWechat,jdbcType=VARCHAR},
      i_nation = #{iNation,jdbcType=VARCHAR},
      i_hometown = #{iHometown,jdbcType=VARCHAR},
      i_naritalstatus = #{iNaritalstatus,jdbcType=VARCHAR},
      i_occupation = #{iOccupation,jdbcType=VARCHAR},
      i_faith = #{iFaith,jdbcType=VARCHAR},
      i_drinkwine = #{iDrinkwine,jdbcType=VARCHAR},
      i_smoking = #{iSmoking,jdbcType=VARCHAR},
      i_sortinhome = #{iSortinhome,jdbcType=VARCHAR},
      i_hasson = #{iHasson,jdbcType=VARCHAR},
      i_weight = #{iWeight,jdbcType=VARCHAR},
      s_age = #{sAge,jdbcType=VARCHAR},
      s_height = #{sHeight,jdbcType=VARCHAR},
      s_annualincome = #{sAnnualincome,jdbcType=VARCHAR},
      s_hometown = #{sHometown,jdbcType=VARCHAR},
      s_maritalstatus = #{sMaritalstatus,jdbcType=VARCHAR},
      s_faith = #{sFaith,jdbcType=VARCHAR},
      s_drink = #{sDrink,jdbcType=VARCHAR},
      s_smoking = #{sSmoking,jdbcType=VARCHAR},
      s_hasson = #{sHasson,jdbcType=VARCHAR},
      s_weight = #{sWeight,jdbcType=VARCHAR},
      s_constellation = #{sConstellation,jdbcType=VARCHAR},
      p_moive = #{pMoive,jdbcType=VARCHAR},
      p_music = #{pMusic,jdbcType=VARCHAR},
      p_book = #{pBook,jdbcType=VARCHAR},
      p_food = #{pFood,jdbcType=VARCHAR},
      p_sport = #{pSport,jdbcType=VARCHAR},
      iduserextrainfo = #{iduserextrainfo,jdbcType=VARCHAR},
      iduser = #{iduser,jdbcType=VARCHAR},
      addtime = #{addtime,jdbcType=TIMESTAMP},
      ts = #{ts,jdbcType=TIMESTAMP}
    where iduserinfo = #{iduserinfo,jdbcType=VARCHAR}
  </update>
</mapper>